odoo/addons/sale_wishlist/README.rst
odoo/addons/sale_wishlist/__init__.py
odoo/addons/sale_wishlist/__manifest__.py
odoo/addons/sale_wishlist/i18n/es.po
odoo/addons/sale_wishlist/i18n/fr_FR.po
odoo/addons/sale_wishlist/i18n/sale_wishlist.pot
odoo/addons/sale_wishlist/models/__init__.py
odoo/addons/sale_wishlist/models/product_set.py
odoo/addons/sale_wishlist/models/res_partner.py
odoo/addons/sale_wishlist/readme/CONTRIBUTORS.rst
odoo/addons/sale_wishlist/readme/CREDITS.rst
odoo/addons/sale_wishlist/readme/DESCRIPTION.rst
odoo/addons/sale_wishlist/readme/USAGE.rst
odoo/addons/sale_wishlist/static/description/icon.png
odoo/addons/sale_wishlist/static/description/index.html
odoo/addons/sale_wishlist/tests/__init__.py
odoo/addons/sale_wishlist/tests/test_wishlist.py
odoo/addons/sale_wishlist/views/partner.xml
odoo/addons/sale_wishlist/views/product_set.xml
odoo14_addon_sale_wishlist-14.0.1.0.2.dist-info/METADATA
odoo14_addon_sale_wishlist-14.0.1.0.2.dist-info/WHEEL
odoo14_addon_sale_wishlist-14.0.1.0.2.dist-info/top_level.txt
odoo14_addon_sale_wishlist-14.0.1.0.2.dist-info/RECORD
